deathsdungeon/__init__.py
deathsdungeon/main.py
deathsdungeon/battle/__init__.py
deathsdungeon/battle/battle.py
deathsdungeon/battle/bossfight.py
deathsdungeon/battle/buff.py
deathsdungeon/battle/die.py
deathsdungeon/battle/enemy.py
deathsdungeon/classes/__init__.py
deathsdungeon/classes/armor.py
deathsdungeon/classes/player.py
deathsdungeon/classes/player_from_dict.py
deathsdungeon/classes/weapon.py
deathsdungeon/code/__init__.py
deathsdungeon/code/game.py
deathsdungeon/code/map.py
deathsdungeon/code/randomness.py
deathsdungeon/code/read.py
deathsdungeon/code/terminal.py
deathsdungeon/code/util.py
deathsdungeon/generators/__init__.py
deathsdungeon/generators/dungeon.py
deathsdungeon/generators/monsters.py
deathsdungeon/people/__init__.py
deathsdungeon/people/chat.py
deathsdungeon/people/grarlan.py
deathsdungeon/people/laurence.py
deathsdungeon/people/maximus.py
deathsdungeon/people/rohan.py
deathsdungeon/people/trekker.py
deathsdungeon/people/warren.py
deathsdungeon/save_game/__init__.py
deathsdungeon/save_game/menu.py
deathsdungeon/save_game/save.py
deathsdungeon/story/__init__.py
deathdungeon_JankyCoder-0.0.1.dist-info/LICENSE
deathdungeon_JankyCoder-0.0.1.dist-info/METADATA
deathdungeon_JankyCoder-0.0.1.dist-info/WHEEL
deathdungeon_JankyCoder-0.0.1.dist-info/top_level.txt
deathdungeon_JankyCoder-0.0.1.dist-info/RECORD
